IHEWAdataanalysis/__init__.py
IHEWAdataanalysis/analysis.py
IHEWAdataanalysis/exception.py
IHEWAdataanalysis/indicators.py
IHEWAdataanalysis/scripts/__init__.py
IHEWAdataanalysis/scripts/main.py
IHEWAdataanalysis/scripts/skeleton.py
IHEWAdataanalysis/templates/__init__.py
IHEWAdataanalysis/templates/util.py
IHEWAdataanalysis/templates/IHE/FAO.py
IHEWAdataanalysis/templates/IHE/FAO.yml
IHEWAdataanalysis/templates/IHE/Manual.yml
IHEWAdataanalysis/templates/IHE/__init__.py
IHEWAdataanalysis-0.0.1.dist-info/AUTHORS.rst
IHEWAdataanalysis-0.0.1.dist-info/LICENSE
IHEWAdataanalysis-0.0.1.dist-info/LICENSE.rst
IHEWAdataanalysis-0.0.1.dist-info/METADATA
IHEWAdataanalysis-0.0.1.dist-info/WHEEL
IHEWAdataanalysis-0.0.1.dist-info/entry_points.txt
IHEWAdataanalysis-0.0.1.dist-info/top_level.txt
IHEWAdataanalysis-0.0.1.dist-info/RECORD
